ql/__init__.py
ql/loop.py
ql/py.typed
ql/utils.py
quantum_loop-0.3.7.dist-info/METADATA
quantum_loop-0.3.7.dist-info/WHEEL
quantum_loop-0.3.7.dist-info/licenses/LICENSE
quantum_loop-0.3.7.dist-info/RECORD
