Metadata-Version: 2.4
Name: quantum-loop
Version: 0.3.7
Summary: A set of tools for quantum calculations.
Project-URL: Homepage, https://kebasyaty.github.io/quantum-loop/
Project-URL: Repository, https://github.com/kebasyaty/quantum-loop
Project-URL: Source, https://github.com/kebasyaty/quantum-loop
Project-URL: Bug Tracker, https://github.com/kebasyaty/quantum-loop/issues
Project-URL: Changelog, https://github.com/kebasyaty/quantum-loop/blob/v0/CHANGELOG.md
Author-email: kebasyaty <kebasyaty@gmail.com>
License-Expression: MIT
License-File: LICENSE
Keywords: loop,quantum,quantum-loop,qubit
Classifier: Development Status :: 4 - Beta
Classifier: Intended Audience :: Developers
Classifier: License :: OSI Approved :: MIT License
Classifier: Operating System :: MacOS :: MacOS X
Classifier: Operating System :: Microsoft :: Windows
Classifier: Operating System :: POSIX
Classifier: Operating System :: POSIX :: Linux
Classifier: Programming Language :: Python :: 3
Classifier: Programming Language :: Python :: 3 :: Only
Classifier: Programming Language :: Python :: 3.12
Classifier: Programming Language :: Python :: 3.13
Classifier: Programming Language :: Python :: 3.14
Classifier: Programming Language :: Python :: Implementation :: CPython
Classifier: Topic :: Software Development :: Libraries
Classifier: Topic :: Software Development :: Libraries :: Python Modules
Classifier: Typing :: Typed
Requires-Python: <4.0,>=3.12
